green_magic/__init__.py
green_magic/definitions.py
green_magic/features.py
green_magic/labeling.py
green_magic/map_maker.py
green_magic/utils.py
green_magic/weedata.py
green_magic/weedmaster.py
green_magic/clustering/__init__.py
green_magic/clustering/cluster.py
green_magic/clustering/cluster_evaluation.py
green_magic/clustering/helpers.py
green_magic-0.5.3.dist-info/DESCRIPTION.rst
green_magic-0.5.3.dist-info/METADATA
green_magic-0.5.3.dist-info/RECORD
green_magic-0.5.3.dist-info/WHEEL
green_magic-0.5.3.dist-info/metadata.json
green_magic-0.5.3.dist-info/top_level.txt
