Metadata-Version: 2.0
Name: green-magic
Version: 0.5.3
Summary: The Green Magic library of the Green-Machine
Home-page: https://github.com/boromir674/green-magic
Author: Konstantinos
Author-email: k.lampridis@hotmail.com
License: GNU GPLv3
Keywords: cannabis strain self-organizing maps visualization
Platform: UNKNOWN
Classifier: Development Status :: 4 - Beta
Classifier: License :: OSI Approved :: GNU General Public License v3 (GPLv3)
Classifier: Programming Language :: Python :: 3.5
Classifier: Topic :: Software Development :: Libraries :: Python Modules
Classifier: Topic :: Scientific/Engineering :: Artificial Intelligence
Classifier: Topic :: Scientific/Engineering :: Visualization
Classifier: Intended Audience :: Science/Research
Requires-Dist: numpy
Requires-Dist: nltk
Requires-Dist: sklearn
Requires-Dist: somoclu
